regexgen/__init__.py
regexgen/operators.py
regexgen/exact/__init__.py
regexgen/exact/brzozowski.py
regexgen/exact/expressions.py
regexgen/exact/hopcroft.py
regexgen/exact/operators.py
regexgen/exact/state.py
regexgen/exact/trie.py
regexgen/fuzzy/__init__.py
regexgen/fuzzy/patterns.py
regexgen/fuzzy/regEx.py
regexgen/fuzzy/util.py
regexgen-1.0.1.dist-info/LICENSE
regexgen-1.0.1.dist-info/METADATA
regexgen-1.0.1.dist-info/WHEEL
regexgen-1.0.1.dist-info/top_level.txt
regexgen-1.0.1.dist-info/RECORD
