Metadata-Version: 2.1
Name: regexgen
Version: 1.0.1
Summary: Turn list of strings to minimal regex. Also supports turning a list of string into a minimal grouped expression. 
Home-page: UNKNOWN
Author: Jo-Frederik Krohn
Author-email: jo-frederik.krohn@accenture.com
License: UNKNOWN
Keywords: regex
Platform: UNKNOWN
Classifier: Programming Language :: Python :: 3
Classifier: Operating System :: OS Independent
Requires-Dist: numpy (==1.14.3)
Requires-Dist: pytest (==3.6)
